{
  "CS 101": {
    "course_avg_gpa": 3.41,
    "professors": {
      "Liia M Butler": {
        "avg_gpa": 3.56,
        "n": 746
      },
      "Mattox A Beckman": {
        "avg_gpa": 3.54,
        "n": 1554
      },
      "Ruby Tahboub": {
        "avg_gpa": 3.67,
        "n": 656
      },
      "Neal E Davis": {
        "avg_gpa": 3.62,
        "n": 7550
      },
      "Ryan M Cunningham": {
        "avg_gpa": 3.26,
        "n": 1382
      },
      "Thomas N Gambill": {
        "avg_gpa": 3.04,
        "n": 4960
      },
      "Saeidreza Shifteh Far": {
        "avg_gpa": 3.03,
        "n": 75
      },
      "Rajesh Bhasin": {
        "avg_gpa": 3.24,
        "n": 78
      },
      "Andrew E Fister": {
        "avg_gpa": 3.29,
        "n": 77
      },
      "Piyush Gupta": {
        "avg_gpa": 3.35,
        "n": 79
      },
      "Zu C Huang": {
        "avg_gpa": 3.15,
        "n": 76
      },
      "Lu Su": {
        "avg_gpa": 3.14,
        "n": 70
      }
    }
  },
  "CS 105": {
    "course_avg_gpa": 3.25,
    "professors": {
      "Maxwell L Fowler": {
        "avg_gpa": 3.38,
        "n": 757
      },
      "Colleen M Lewis": {
        "avg_gpa": 2.99,
        "n": 1278
      },
      "Craig Zilles": {
        "avg_gpa": 3.16,
        "n": 3395
      },
      "David H Smith": {
        "avg_gpa": 2.71,
        "n": 30
      },
      "Albert F Harris": {
        "avg_gpa": 3.39,
        "n": 2746
      },
      "Michael Haberman": {
        "avg_gpa": 3.46,
        "n": 544
      },
      "Martin Hellwig": {
        "avg_gpa": 3.56,
        "n": 1168
      },
      "Wade A Fagen": {
        "avg_gpa": 3.32,
        "n": 2581
      },
      "Kai Zhao": {
        "avg_gpa": 3.3,
        "n": 2214
      },
      "Thomas N Gambill": {
        "avg_gpa": 3.1,
        "n": 1649
      },
      "Steven T Lauterburg": {
        "avg_gpa": 2.95,
        "n": 512
      },
      "Minas Charalambides": {
        "avg_gpa": 3.06,
        "n": 77
      },
      "Boonrod Yuttanan": {
        "avg_gpa": 2.66,
        "n": 34
      },
      "Ankeeth S Ved": {
        "avg_gpa": 3.09,
        "n": 77
      },
      "Aditya Zutshi": {
        "avg_gpa": 2.79,
        "n": 81
      },
      "Chaitanya P Date": {
        "avg_gpa": 3.22,
        "n": 64
      },
      "Christopher R Hsiao": {
        "avg_gpa": 3.07,
        "n": 76
      },
      "Aditya Bhagath": {
        "avg_gpa": 3.16,
        "n": 27
      },
      "Damion R Mitchell": {
        "avg_gpa": 3.07,
        "n": 62
      },
      "Yi-Shuan Chen": {
        "avg_gpa": 3.16,
        "n": 81
      },
      "Ankit Saharan": {
        "avg_gpa": 3.26,
        "n": 67
      }
    }
  },
  "CS 124": {
    "course_avg_gpa": 3.6,
    "professors": {
      "Geoffrey W Challen": {
        "avg_gpa": 3.6,
        "n": 7191
      }
    }
  },
  "CS 128": {
    "course_avg_gpa": 3.58,
    "professors": {
      "Michael Nowak": {
        "avg_gpa": 3.58,
        "n": 5874
      },
      "Jule Schatz": {
        "avg_gpa": 3.65,
        "n": 64
      }
    }
  },
  "CS 173": {
    "course_avg_gpa": 3.07,
    "professors": {
      "Margaret M Fleck": {
        "avg_gpa": 3.0,
        "n": 7595
      },
      "Graham C Evans": {
        "avg_gpa": 3.14,
        "n": 1051
      },
      "Benjamin L Cosman": {
        "avg_gpa": 3.12,
        "n": 2943
      },
      "Naina Balepur": {
        "avg_gpa": 3.18,
        "n": 267
      },
      "Payam Delgosha": {
        "avg_gpa": 3.16,
        "n": 1205
      },
      "Madhusudan Parthasarathy": {
        "avg_gpa": 3.0,
        "n": 158
      },
      "Brad R Solomon": {
        "avg_gpa": 3.0,
        "n": 165
      },
      "Qian Zhou": {
        "avg_gpa": 3.13,
        "n": 199
      },
      "Ian G Ludden": {
        "avg_gpa": 3.59,
        "n": 94
      },
      "Patrick Lin": {
        "avg_gpa": 3.39,
        "n": 170
      },
      "Mahesh Viswanathan": {
        "avg_gpa": 3.27,
        "n": 696
      },
      "David Varodayan": {
        "avg_gpa": 2.93,
        "n": 192
      },
      "Tandy Warnow": {
        "avg_gpa": 3.2,
        "n": 189
      },
      "Jose Meseguer": {
        "avg_gpa": 2.88,
        "n": 130
      },
      "Yipu Wang": {
        "avg_gpa": 3.18,
        "n": 65
      },
      "Lance C Pittman": {
        "avg_gpa": 2.87,
        "n": 88
      },
      "Chen Li": {
        "avg_gpa": 2.55,
        "n": 52
      },
      "Samer R Fanek": {
        "avg_gpa": 2.47,
        "n": 52
      },
      "Lucas T Cook": {
        "avg_gpa": 2.71,
        "n": 49
      }
    }
  },
  "CS 210": {
    "course_avg_gpa": 3.63,
    "professors": {
      "Ryan M Cunningham": {
        "avg_gpa": 3.65,
        "n": 2296
      },
      "Joshua T Asplund": {
        "avg_gpa": 3.7,
        "n": 242
      },
      "Alex Kirlik": {
        "avg_gpa": 3.43,
        "n": 365
      },
      "Keith W Miller": {
        "avg_gpa": 3.39,
        "n": 89
      },
      "Marsha C Woodbury": {
        "avg_gpa": 3.76,
        "n": 287
      },
      "Michael C Loui": {
        "avg_gpa": 3.63,
        "n": 114
      }
    }
  },
  "CS 211": {
    "course_avg_gpa": 3.72,
    "professors": {
      "Ryan M Cunningham": {
        "avg_gpa": 3.72,
        "n": 845
      }
    }
  },
  "CS 222": {
    "course_avg_gpa": 3.87,
    "professors": {
      "Michael J Woodley": {
        "avg_gpa": 3.87,
        "n": 2683
      }
    }
  },
  "CS 225": {
    "course_avg_gpa": 3.27,
    "professors": {
      "Graham C Evans": {
        "avg_gpa": 3.49,
        "n": 6556
      },
      "Volodymyr Kindratenko": {
        "avg_gpa": 3.5,
        "n": 205
      },
      "Brad R Solomon": {
        "avg_gpa": 3.48,
        "n": 2013
      },
      "Craig Zilles": {
        "avg_gpa": 3.18,
        "n": 458
      },
      "Wade A Fagen-Ulmschnei": {
        "avg_gpa": 3.22,
        "n": 2008
      },
      "Cinda Heeren": {
        "avg_gpa": 3.05,
        "n": 6130
      },
      "Ganna Yershova": {
        "avg_gpa": 2.84,
        "n": 71
      },
      "Chase A Geigle": {
        "avg_gpa": 2.85,
        "n": 305
      },
      "Sean A Massung": {
        "avg_gpa": 2.8,
        "n": 56
      },
      "John D Toole": {
        "avg_gpa": 2.6,
        "n": 110
      },
      "Debessay F Kassa": {
        "avg_gpa": 2.49,
        "n": 25
      },
      "Ibrahim Karahan": {
        "avg_gpa": 2.23,
        "n": 51
      },
      "John C Earls": {
        "avg_gpa": 2.88,
        "n": 75
      },
      "Varun K Singh": {
        "avg_gpa": 2.46,
        "n": 23
      }
    }
  },
  "CS 233": {
    "course_avg_gpa": 3.35,
    "professors": {
      "Craig Zilles": {
        "avg_gpa": 3.09,
        "n": 1935
      },
      "Geoffrey L Herman": {
        "avg_gpa": 3.46,
        "n": 4626
      },
      "Ryan Wong": {
        "avg_gpa": 3.8,
        "n": 25
      },
      "Shoaib A Meenai": {
        "avg_gpa": 3.16,
        "n": 66
      }
    }
  },
  "CS 277": {
    "course_avg_gpa": 3.6,
    "professors": {
      "Brad R Solomon": {
        "avg_gpa": 3.6,
        "n": 302
      }
    }
  },
  "CS 307": {
    "course_avg_gpa": 3.76,
    "professors": {
      "David M Dalpiaz": {
        "avg_gpa": 3.76,
        "n": 381
      }
    }
  },
  "CS 340": {
    "course_avg_gpa": 3.46,
    "professors": {
      "Luther A Tychonievich": {
        "avg_gpa": 3.51,
        "n": 511
      },
      "Graham C Evans": {
        "avg_gpa": 3.54,
        "n": 139
      },
      "Wade A Fagen-Ulmschnei": {
        "avg_gpa": 3.33,
        "n": 261
      }
    }
  },
  "CS 341": {
    "course_avg_gpa": 3.66,
    "professors": {
      "Lawrence Angrave": {
        "avg_gpa": 3.66,
        "n": 1773
      }
    }
  },
  "CS 357": {
    "course_avg_gpa": 3.27,
    "professors": {
      "Mariana T Silva": {
        "avg_gpa": 3.4,
        "n": 5827
      },
      "Luke Olson": {
        "avg_gpa": 3.03,
        "n": 631
      },
      "Andreas P Kloeckner": {
        "avg_gpa": 3.03,
        "n": 1011
      },
      "Michael T Heath": {
        "avg_gpa": 2.68,
        "n": 184
      },
      "Eric G Shaffer": {
        "avg_gpa": 3.11,
        "n": 442
      },
      "Bart D Semeraro": {
        "avg_gpa": 2.99,
        "n": 384
      },
      "Thomas N Gambill": {
        "avg_gpa": 3.3,
        "n": 253
      },
      "Anil N Hirani": {
        "avg_gpa": 2.82,
        "n": 236
      },
      "Ganna Yershova": {
        "avg_gpa": 3.13,
        "n": 165
      },
      "William D Gropp": {
        "avg_gpa": 3.32,
        "n": 146
      }
    }
  },
  "CS 361": {
    "course_avg_gpa": 3.44,
    "professors": {
      "Hongye Liu": {
        "avg_gpa": 3.46,
        "n": 2982
      },
      "David Varodayan": {
        "avg_gpa": 3.14,
        "n": 219
      },
      "Richard C Barber": {
        "avg_gpa": 3.29,
        "n": 115
      },
      "Saurabh Sinha": {
        "avg_gpa": 3.41,
        "n": 64
      },
      "Jian Peng": {
        "avg_gpa": 3.37,
        "n": 66
      }
    }
  },
  "CS 374": {
    "course_avg_gpa": 2.89,
    "professors": {
      "Chandra S Chekuri": {
        "avg_gpa": 2.84,
        "n": 1943
      },
      "Abhishek Kumar Umrawal": {
        "avg_gpa": 3.18,
        "n": 519
      },
      "Sariel Har-Peled": {
        "avg_gpa": 2.78,
        "n": 1668
      },
      "Ivan T Abraham": {
        "avg_gpa": 3.22,
        "n": 317
      },
      "Ruta Mehta": {
        "avg_gpa": 2.99,
        "n": 428
      },
      "Jeff G Erickson": {
        "avg_gpa": 2.73,
        "n": 1747
      },
      "Nickvash Kani": {
        "avg_gpa": 3.24,
        "n": 1196
      },
      "Timothy M Chan": {
        "avg_gpa": 2.89,
        "n": 334
      },
      "Andrew E Miller": {
        "avg_gpa": 2.85,
        "n": 175
      },
      "Nikita Borisov": {
        "avg_gpa": 2.63,
        "n": 218
      },
      "Haitham Al-Hassanieh": {
        "avg_gpa": 2.61,
        "n": 153
      },
      "Mahesh Viswanathan": {
        "avg_gpa": 2.67,
        "n": 264
      }
    }
  },
  "CS 410": {
    "course_avg_gpa": 3.87,
    "professors": {
      "Pablo D Robles Granda": {
        "avg_gpa": 3.91,
        "n": 531
      },
      "Chengxiang Zhai": {
        "avg_gpa": 3.86,
        "n": 3586
      },
      "Sean A Massung": {
        "avg_gpa": 3.58,
        "n": 23
      }
    }
  },
  "CS 411": {
    "course_avg_gpa": 3.59,
    "professors": {
      "Kevin C Chang": {
        "avg_gpa": 3.41,
        "n": 2455
      },
      "Abdussalam A Alawini": {
        "avg_gpa": 3.72,
        "n": 6375
      },
      "Yongjoo Park": {
        "avg_gpa": 3.78,
        "n": 44
      },
      "Aditya G Parameswaran": {
        "avg_gpa": 3.49,
        "n": 604
      },
      "Saurabh Sinha": {
        "avg_gpa": 3.3,
        "n": 700
      },
      "Ryan M Cunningham": {
        "avg_gpa": 3.57,
        "n": 378
      },
      "Timothy E Weninger": {
        "avg_gpa": 3.54,
        "n": 56
      },
      "Peixiang Zhao": {
        "avg_gpa": 3.1,
        "n": 168
      }
    }
  },
  "CS 412": {
    "course_avg_gpa": 3.42,
    "professors": {
      "Ruby Tahboub": {
        "avg_gpa": 3.71,
        "n": 564
      },
      "Arindam Banerjee": {
        "avg_gpa": 3.54,
        "n": 916
      },
      "Jiawei Han": {
        "avg_gpa": 3.43,
        "n": 2367
      },
      "Hanghang Tong": {
        "avg_gpa": 3.29,
        "n": 534
      },
      "Saurabh Sinha": {
        "avg_gpa": 3.19,
        "n": 177
      },
      "Qi Li": {
        "avg_gpa": 3.34,
        "n": 266
      },
      "Hari Sundaram": {
        "avg_gpa": 3.42,
        "n": 373
      },
      "Meng Jiang": {
        "avg_gpa": 3.37,
        "n": 70
      },
      "Kevin C Chang": {
        "avg_gpa": 2.93,
        "n": 358
      }
    }
  },
  "CS 415": {
    "course_avg_gpa": 3.75,
    "professors": {
      "Eric G Shaffer": {
        "avg_gpa": 3.75,
        "n": 1382
      }
    }
  },
  "CS 421": {
    "course_avg_gpa": 3.41,
    "professors": {
      "Mattox A Beckman": {
        "avg_gpa": 3.54,
        "n": 2381
      },
      "Sasa Misailovic": {
        "avg_gpa": 3.44,
        "n": 328
      },
      "Elsa Gunter": {
        "avg_gpa": 3.33,
        "n": 2877
      },
      "Talia L Ringer": {
        "avg_gpa": 3.45,
        "n": 77
      },
      "Liia M Butler": {
        "avg_gpa": 3.67,
        "n": 136
      },
      "A M Beckman": {
        "avg_gpa": 3.49,
        "n": 1189
      },
      "Madhusudan Parthasarathy": {
        "avg_gpa": 3.54,
        "n": 105
      },
      "Gul A Agha": {
        "avg_gpa": 3.39,
        "n": 166
      },
      "Kaushik Kalyanaraman": {
        "avg_gpa": 3.42,
        "n": 30
      },
      "Grigore Rosu": {
        "avg_gpa": 3.04,
        "n": 179
      },
      "Kirill A Mechitov": {
        "avg_gpa": 3.13,
        "n": 21
      },
      "Samuel N Kamin": {
        "avg_gpa": 3.12,
        "n": 366
      },
      "William E Mansky": {
        "avg_gpa": 3.07,
        "n": 34
      },
      "Dennis E Griffith": {
        "avg_gpa": 2.68,
        "n": 42
      },
      "Munawar Hafiz": {
        "avg_gpa": 2.9,
        "n": 30
      }
    }
  },
  "CS 423": {
    "course_avg_gpa": 3.51,
    "professors": {
      "Ramnatthan Alagappan": {
        "avg_gpa": 3.89,
        "n": 61
      },
      "Tianyin Xu": {
        "avg_gpa": 3.64,
        "n": 326
      },
      "Wade A Fagen-Ulmschnei": {
        "avg_gpa": 3.54,
        "n": 84
      },
      "Adam M Bates": {
        "avg_gpa": 3.04,
        "n": 233
      },
      "Tarek Abdelzaher": {
        "avg_gpa": 3.65,
        "n": 417
      },
      "Klara Nahrstedt": {
        "avg_gpa": 3.38,
        "n": 85
      },
      "Elsa Gunter": {
        "avg_gpa": 3.33,
        "n": 33
      },
      "R H Campbell": {
        "avg_gpa": 3.59,
        "n": 32
      }
    }
  },
  "CS 425": {
    "course_avg_gpa": 3.32,
    "professors": {
      "Radhika Mittal": {
        "avg_gpa": 3.16,
        "n": 856
      },
      "Indranil Gupta": {
        "avg_gpa": 3.46,
        "n": 3335
      },
      "Nikita Borisov": {
        "avg_gpa": 3.06,
        "n": 729
      },
      "Nitin H Vaidya": {
        "avg_gpa": 3.16,
        "n": 651
      },
      "Mirko Montanari": {
        "avg_gpa": 3.47,
        "n": 48
      },
      "Shishir Nagaraja": {
        "avg_gpa": 2.56,
        "n": 34
      }
    }
  },
  "CS 427": {
    "course_avg_gpa": 3.64,
    "professors": {
      "Darko Marinov": {
        "avg_gpa": 3.55,
        "n": 661
      },
      "Lingming Zhang": {
        "avg_gpa": 3.77,
        "n": 584
      },
      "Reyhaneh Jabbarvand Behr": {
        "avg_gpa": 3.78,
        "n": 714
      },
      "Grigore Rosu": {
        "avg_gpa": 3.35,
        "n": 409
      },
      "nan": {
        "avg_gpa": 3.89,
        "n": 102
      },
      "Tao Xie": {
        "avg_gpa": 3.65,
        "n": 318
      },
      "Daniel Dig": {
        "avg_gpa": 3.44,
        "n": 144
      },
      "Ralph E Johnson": {
        "avg_gpa": 3.56,
        "n": 100
      }
    }
  },
  "CS 431": {
    "course_avg_gpa": 3.1,
    "professors": {
      "Lui R Sha": {
        "avg_gpa": 3.37,
        "n": 557
      },
      "Marco Caccamo": {
        "avg_gpa": 2.73,
        "n": 403
      }
    }
  },
  "CS 433": {
    "course_avg_gpa": 3.35,
    "professors": {
      "Sarita V Adve": {
        "avg_gpa": 3.36,
        "n": 589
      },
      "Saugata Ghose": {
        "avg_gpa": 3.26,
        "n": 133
      },
      "Christopher W Fletcher": {
        "avg_gpa": 3.49,
        "n": 160
      },
      "Josep Torrellas": {
        "avg_gpa": 3.28,
        "n": 99
      },
      "Maria J Garzaran": {
        "avg_gpa": 3.09,
        "n": 21
      }
    }
  },
  "CS 435": {
    "course_avg_gpa": 3.66,
    "professors": {
      "Philip B Godfrey": {
        "avg_gpa": 3.66,
        "n": 649
      }
    }
  },
  "CS 437": {
    "course_avg_gpa": 3.69,
    "professors": {
      "Matthew C Caesar": {
        "avg_gpa": 3.69,
        "n": 1088
      }
    }
  },
  "CS 438": {
    "course_avg_gpa": 3.26,
    "professors": {
      "Elahe Soltanaghai": {
        "avg_gpa": 3.53,
        "n": 157
      },
      "Yu-Lin Wei": {
        "avg_gpa": 3.58,
        "n": 171
      },
      "Deepak Vasisht": {
        "avg_gpa": 3.6,
        "n": 386
      },
      "Romit Roy Choudhury": {
        "avg_gpa": 3.52,
        "n": 840
      },
      "Haitham Al-Hassanieh": {
        "avg_gpa": 3.43,
        "n": 183
      },
      "Robin H Kravets": {
        "avg_gpa": 2.62,
        "n": 456
      },
      "Nikita Borisov": {
        "avg_gpa": 2.62,
        "n": 81
      },
      "Matthew C Caesar": {
        "avg_gpa": 2.55,
        "n": 107
      },
      "Nitin H Vaidya": {
        "avg_gpa": 3.07,
        "n": 147
      },
      "Philip B Godfrey": {
        "avg_gpa": 2.57,
        "n": 35
      },
      "Steven S Lumetta": {
        "avg_gpa": 3.23,
        "n": 52
      }
    }
  },
  "CS 440": {
    "course_avg_gpa": 3.36,
    "professors": {
      "Mark A Hasegawa-Johnso": {
        "avg_gpa": 3.51,
        "n": 3273
      },
      "Margaret M Fleck": {
        "avg_gpa": 3.36,
        "n": 2363
      },
      "Julia C Hockenmaier": {
        "avg_gpa": 3.09,
        "n": 176
      },
      "Svetlana Lazebnik": {
        "avg_gpa": 3.22,
        "n": 981
      },
      "Gerald F DeJong": {
        "avg_gpa": 3.03,
        "n": 707
      },
      "Gerald F Dejong": {
        "avg_gpa": 2.89,
        "n": 65
      },
      "Eyal Amir": {
        "avg_gpa": 2.99,
        "n": 60
      }
    }
  },
  "CS 441": {
    "course_avg_gpa": 3.81,
    "professors": {
      "Marco An Morales Aguirre": {
        "avg_gpa": 3.79,
        "n": 4047
      },
      "Derek W Hoiem": {
        "avg_gpa": 3.88,
        "n": 901
      }
    }
  },
  "CS 442": {
    "course_avg_gpa": 3.18,
    "professors": {
      "Han Zhao": {
        "avg_gpa": 3.18,
        "n": 73
      }
    }
  },
  "CS 444": {
    "course_avg_gpa": 3.7,
    "professors": {
      "Svetlana Lazebnik": {
        "avg_gpa": 3.76,
        "n": 1043
      },
      "Saurabh Gupta": {
        "avg_gpa": 3.4,
        "n": 207
      }
    }
  },
  "CS 445": {
    "course_avg_gpa": 3.57,
    "professors": {
      "Derek W Hoiem": {
        "avg_gpa": 3.6,
        "n": 1210
      },
      "Yuxiong Wang": {
        "avg_gpa": 3.52,
        "n": 729
      }
    }
  },
  "CS 446": {
    "course_avg_gpa": 3.4,
    "professors": {
      "Tong Zhang": {
        "avg_gpa": 3.46,
        "n": 131
      },
      "Liangyan Gui": {
        "avg_gpa": 3.53,
        "n": 452
      },
      "Shenlong Wang": {
        "avg_gpa": 3.45,
        "n": 144
      },
      "Matus J Telgarsky": {
        "avg_gpa": 3.39,
        "n": 797
      },
      "Alexander G Schwing": {
        "avg_gpa": 3.44,
        "n": 488
      },
      "Oluwasanmi O Koyejo": {
        "avg_gpa": 3.32,
        "n": 501
      },
      "Dan Roth": {
        "avg_gpa": 3.4,
        "n": 620
      },
      "Julia C Hockenmaier": {
        "avg_gpa": 3.22,
        "n": 227
      }
    }
  },
  "CS 447": {
    "course_avg_gpa": 3.64,
    "professors": {
      "Julia C Hockenmaier": {
        "avg_gpa": 3.64,
        "n": 1782
      }
    }
  },
  "CS 448": {
    "course_avg_gpa": 3.55,
    "professors": {
      "Paris Smaragdis": {
        "avg_gpa": 3.55,
        "n": 228
      }
    }
  },
  "CS 450": {
    "course_avg_gpa": 3.17,
    "professors": {
      "Paul Fischer": {
        "avg_gpa": 3.26,
        "n": 808
      },
      "Andreas P Kloeckner": {
        "avg_gpa": 3.22,
        "n": 741
      },
      "Edgar Solomonik": {
        "avg_gpa": 3.29,
        "n": 106
      },
      "Edgar V Solomonik": {
        "avg_gpa": 3.27,
        "n": 440
      },
      "Luke Olson": {
        "avg_gpa": 2.99,
        "n": 429
      },
      "Eric G Shaffer": {
        "avg_gpa": 3.26,
        "n": 22
      },
      "Michael T Heath": {
        "avg_gpa": 3.12,
        "n": 454
      },
      "Anil N Hirani": {
        "avg_gpa": 2.84,
        "n": 145
      },
      "Stephen Bond": {
        "avg_gpa": 2.86,
        "n": 39
      }
    }
  },
  "CS 461": {
    "course_avg_gpa": 3.02,
    "professors": {
      "Ling Ren": {
        "avg_gpa": 2.97,
        "n": 479
      },
      "Nikita Borisov": {
        "avg_gpa": 2.98,
        "n": 111
      },
      "Kirill I Levchenko": {
        "avg_gpa": 2.86,
        "n": 190
      },
      "Adam Bates": {
        "avg_gpa": 2.89,
        "n": 76
      },
      "Michael D Bailey": {
        "avg_gpa": 2.91,
        "n": 1060
      },
      "Adam M Bates": {
        "avg_gpa": 2.64,
        "n": 146
      },
      "Ryan M Cunningham": {
        "avg_gpa": 3.45,
        "n": 565
      },
      "nan": {
        "avg_gpa": 2.95,
        "n": 317
      },
      "Rakesh Bobba": {
        "avg_gpa": 3.04,
        "n": 187
      },
      "David M Nicol": {
        "avg_gpa": 3.03,
        "n": 154
      },
      "Susan Hinrichs": {
        "avg_gpa": 3.04,
        "n": 353
      }
    }
  },
  "CS 463": {
    "course_avg_gpa": 3.61,
    "professors": {
      "Gang Wang": {
        "avg_gpa": 3.8,
        "n": 480
      },
      "Varun Chandrasekaran": {
        "avg_gpa": 3.56,
        "n": 97
      },
      "Carl Gunter": {
        "avg_gpa": 3.29,
        "n": 271
      }
    }
  },
  "CS 464": {
    "course_avg_gpa": 3.73,
    "professors": {
      "Camille M Cobb": {
        "avg_gpa": 3.76,
        "n": 101
      },
      "Carl Gunter": {
        "avg_gpa": 3.6,
        "n": 21
      }
    }
  },
  "CS 473": {
    "course_avg_gpa": 2.88,
    "professors": {
      "Timothy M Chan": {
        "avg_gpa": 3.14,
        "n": 154
      },
      "Jeff G Erickson": {
        "avg_gpa": 2.82,
        "n": 712
      },
      "Michael A Forbes": {
        "avg_gpa": 3.06,
        "n": 195
      },
      "Christian J Howard": {
        "avg_gpa": 3.2,
        "n": 35
      },
      "Sariel Har-Peled": {
        "avg_gpa": 2.66,
        "n": 429
      },
      "Ruta Mehta": {
        "avg_gpa": 3.18,
        "n": 105
      },
      "Chandra S Chekuri": {
        "avg_gpa": 2.99,
        "n": 333
      },
      "Alexandra Kolla": {
        "avg_gpa": 2.77,
        "n": 239
      }
    }
  },
  "CS 477": {
    "course_avg_gpa": 3.54,
    "professors": {
      "Gagandeep Singh": {
        "avg_gpa": 3.54,
        "n": 191
      },
      "Sasa Misailovic": {
        "avg_gpa": 3.51,
        "n": 33
      },
      "Elsa Gunter": {
        "avg_gpa": 3.6,
        "n": 65
      },
      "Madhusudan Parthasarathy": {
        "avg_gpa": 3.46,
        "n": 23
      }
    }
  },
  "CS 498": {
    "course_avg_gpa": 3.57,
    "professors": {
      "Reza Farivar": {
        "avg_gpa": 3.61,
        "n": 2736
      },
      "Abdussalam A Alawini": {
        "avg_gpa": 3.8,
        "n": 136
      },
      "Makrand Sinha": {
        "avg_gpa": 3.94,
        "n": 32
      },
      "Eshwar Chandrasekharan": {
        "avg_gpa": 3.87,
        "n": 29
      },
      "Ryan M Cunningham": {
        "avg_gpa": 3.81,
        "n": 225
      },
      "Timothy M Chan": {
        "avg_gpa": 3.24,
        "n": 71
      },
      "David M Dalpiaz": {
        "avg_gpa": 3.91,
        "n": 64
      },
      "Girish Chowdhary": {
        "avg_gpa": 3.79,
        "n": 137
      },
      "Dakshita Khurana": {
        "avg_gpa": 3.92,
        "n": 30
      },
      "Shenlong Wang": {
        "avg_gpa": 3.59,
        "n": 135
      },
      "Hari Sundaram": {
        "avg_gpa": 3.69,
        "n": 328
      },
      "Eric G Shaffer": {
        "avg_gpa": 3.61,
        "n": 1008
      },
      "Kris Hauser": {
        "avg_gpa": 3.49,
        "n": 77
      },
      "Marco An Morales Aguirre": {
        "avg_gpa": 3.77,
        "n": 369
      },
      "H C Lane": {
        "avg_gpa": 3.58,
        "n": 33
      },
      "Ranjitha Kumar": {
        "avg_gpa": 3.31,
        "n": 784
      },
      "Svetlana Lazebnik": {
        "avg_gpa": 3.71,
        "n": 467
      },
      "Ravishankar K Iyer": {
        "avg_gpa": 2.88,
        "n": 80
      },
      "Matthew C Caesar": {
        "avg_gpa": 3.81,
        "n": 297
      },
      "Bo Li": {
        "avg_gpa": 3.71,
        "n": 49
      },
      "Paris Smaragdis": {
        "avg_gpa": 3.71,
        "n": 286
      },
      "Nan Jiang": {
        "avg_gpa": 3.66,
        "n": 94
      },
      "John C Hart": {
        "avg_gpa": 3.77,
        "n": 1842
      },
      "Payam Delgosha": {
        "avg_gpa": 3.92,
        "n": 470
      },
      "Carl Gunter": {
        "avg_gpa": 3.82,
        "n": 89
      },
      "Philip B Godfrey": {
        "avg_gpa": 3.13,
        "n": 149
      },
      "David A Forsyth": {
        "avg_gpa": 3.61,
        "n": 1291
      },
      "Deniz Arsan": {
        "avg_gpa": 3.78,
        "n": 92
      },
      "Andrew E Miller": {
        "avg_gpa": 3.38,
        "n": 24
      },
      "Chandra S Chekuri": {
        "avg_gpa": 2.92,
        "n": 459
      },
      "Trevor A Walker": {
        "avg_gpa": 3.82,
        "n": 507
      },
      "R H Campbell": {
        "avg_gpa": 3.58,
        "n": 446
      },
      "Alex Kirlik": {
        "avg_gpa": 3.33,
        "n": 28
      },
      "Geoffrey L Herman": {
        "avg_gpa": 3.14,
        "n": 21
      },
      "Lawrence C Angrave": {
        "avg_gpa": 3.58,
        "n": 157
      },
      "Ganna Yershova": {
        "avg_gpa": 3.8,
        "n": 429
      },
      "Jeff G Erickson": {
        "avg_gpa": 2.92,
        "n": 323
      },
      "Steven M Lavalle": {
        "avg_gpa": 3.55,
        "n": 374
      },
      "Victoria Stodden": {
        "avg_gpa": 3.82,
        "n": 38
      },
      "Brian P Bailey": {
        "avg_gpa": 3.62,
        "n": 44
      },
      "Mahesh Viswanathan": {
        "avg_gpa": 2.83,
        "n": 367
      },
      "Darko Marinov": {
        "avg_gpa": 3.47,
        "n": 53
      },
      "Sariel Har-Peled": {
        "avg_gpa": 3.19,
        "n": 25
      },
      "Leonard B Pitt": {
        "avg_gpa": 2.6,
        "n": 377
      },
      "Derek W Hoiem": {
        "avg_gpa": 3.66,
        "n": 75
      },
      "Rhiannon L Clifton": {
        "avg_gpa": 3.65,
        "n": 22
      },
      "Wai-Tat Fu": {
        "avg_gpa": 3.29,
        "n": 64
      },
      "David A Padua": {
        "avg_gpa": 2.7,
        "n": 30
      },
      "Samuel T King": {
        "avg_gpa": 3.61,
        "n": 36
      },
      "Guy E Garnett": {
        "avg_gpa": 3.66,
        "n": 35
      }
    }
  },
  "CS 500": {
    "course_avg_gpa": 3.85,
    "professors": {
      "Colleen M Lewis": {
        "avg_gpa": 3.9,
        "n": 65
      },
      "Craig Zilles": {
        "avg_gpa": 3.92,
        "n": 21
      },
      "Kathryn I Cunningham": {
        "avg_gpa": 3.75,
        "n": 52
      }
    }
  },
  "CS 510": {
    "course_avg_gpa": 3.86,
    "professors": {
      "Chengxiang Zhai": {
        "avg_gpa": 3.86,
        "n": 679
      }
    }
  },
  "CS 521": {
    "course_avg_gpa": 3.83,
    "professors": {
      "Grigore Rosu": {
        "avg_gpa": 3.9,
        "n": 35
      },
      "Sasa Misailovic": {
        "avg_gpa": 3.79,
        "n": 36
      },
      "Madhusudan Parthasarathy": {
        "avg_gpa": 3.81,
        "n": 21
      }
    }
  },
  "CS 523": {
    "course_avg_gpa": 3.74,
    "professors": {
      "Tianyin Xu": {
        "avg_gpa": 3.76,
        "n": 185
      },
      "R H Campbell": {
        "avg_gpa": 3.69,
        "n": 64
      }
    }
  },
  "CS 533": {
    "course_avg_gpa": 3.65,
    "professors": {
      "Josep Torrellas": {
        "avg_gpa": 3.65,
        "n": 319
      }
    }
  },
  "CS 534": {
    "course_avg_gpa": 3.66,
    "professors": {
      "Saugata Ghose": {
        "avg_gpa": 3.66,
        "n": 58
      }
    }
  },
  "CS 538": {
    "course_avg_gpa": 3.85,
    "professors": {
      "Francis Y Yan": {
        "avg_gpa": 3.97,
        "n": 51
      },
      "Philip B Godfrey": {
        "avg_gpa": 3.83,
        "n": 219
      },
      "Klara Nahrstedt": {
        "avg_gpa": 3.84,
        "n": 21
      }
    }
  },
  "CS 555": {
    "course_avg_gpa": 3.8,
    "professors": {
      "Luke Olson": {
        "avg_gpa": 3.81,
        "n": 217
      },
      "Andreas P Kloeckner": {
        "avg_gpa": 3.74,
        "n": 56
      },
      "Paul Fischer": {
        "avg_gpa": 3.89,
        "n": 74
      },
      "Anil N Hirani": {
        "avg_gpa": 3.62,
        "n": 28
      }
    }
  },
  "CS 563": {
    "course_avg_gpa": 3.69,
    "professors": {
      "Nikita Borisov": {
        "avg_gpa": 3.78,
        "n": 23
      },
      "Christopher W Fletcher": {
        "avg_gpa": 3.81,
        "n": 88
      },
      "Adam M Bates": {
        "avg_gpa": 3.41,
        "n": 66
      },
      "Carl Gunter": {
        "avg_gpa": 3.88,
        "n": 26
      }
    }
  },
  "CS 568": {
    "course_avg_gpa": 3.93,
    "professors": {
      "Ranjitha Kumar": {
        "avg_gpa": 3.93,
        "n": 390
      }
    }
  },
  "CS 588": {
    "course_avg_gpa": 3.24,
    "professors": {
      "Kris Hauser": {
        "avg_gpa": 3.24,
        "n": 101
      }
    }
  },
  "CS 598": {
    "course_avg_gpa": 3.83,
    "professors": {
      "William S Moses": {
        "avg_gpa": 3.91,
        "n": 22
      },
      "Arindam Banerjee": {
        "avg_gpa": 3.91,
        "n": 81
      },
      "Jimeng Sun": {
        "avg_gpa": 3.84,
        "n": 1580
      },
      "Trevor H Park": {
        "avg_gpa": 3.55,
        "n": 776
      },
      "Fan Lai": {
        "avg_gpa": 3.91,
        "n": 126
      },
      "Aishwarya Ganesan": {
        "avg_gpa": 3.82,
        "n": 26
      },
      "Ge Liu": {
        "avg_gpa": 3.89,
        "n": 33
      },
      "Lingming Zhang": {
        "avg_gpa": 3.83,
        "n": 70
      },
      "Hao Peng": {
        "avg_gpa": 3.91,
        "n": 81
      },
      "Tal M August": {
        "avg_gpa": 3.77,
        "n": 70
      },
      "Yongjoo Park": {
        "avg_gpa": 3.82,
        "n": 182
      },
      "Adam Bates": {
        "avg_gpa": 3.85,
        "n": 22
      },
      "Minjia Zhang": {
        "avg_gpa": 3.72,
        "n": 71
      },
      "Craig A Willis": {
        "avg_gpa": 3.96,
        "n": 676
      },
      "Dilek Hakkani Tur": {
        "avg_gpa": 3.84,
        "n": 65
      },
      "Reyhaneh Jabbarvand Behr": {
        "avg_gpa": 3.91,
        "n": 114
      },
      "Jiawei Han": {
        "avg_gpa": 3.79,
        "n": 87
      },
      "Daniel Kang": {
        "avg_gpa": 3.93,
        "n": 81
      },
      "Kris Hauser": {
        "avg_gpa": 3.42,
        "n": 56
      },
      "Feng Liang": {
        "avg_gpa": 3.82,
        "n": 1361
      },
      "Shenlong Wang": {
        "avg_gpa": 3.97,
        "n": 37
      },
      "Tong Zhang": {
        "avg_gpa": 3.88,
        "n": 84
      },
      "Jiaxuan You": {
        "avg_gpa": 3.93,
        "n": 43
      },
      "David A Heath": {
        "avg_gpa": 3.67,
        "n": 30
      },
      "Girish Chowdhary": {
        "avg_gpa": 3.83,
        "n": 26
      },
      "Julia C Hockenmaier": {
        "avg_gpa": 3.93,
        "n": 50
      },
      "Makrand Sinha": {
        "avg_gpa": 3.96,
        "n": 24
      },
      "Yunzhu Li": {
        "avg_gpa": 3.87,
        "n": 55
      },
      "Reza Farivar": {
        "avg_gpa": 3.88,
        "n": 350
      },
      "Ramnatthan Alagappan": {
        "avg_gpa": 3.86,
        "n": 41
      },
      "Sarah G Sterman": {
        "avg_gpa": 3.91,
        "n": 32
      },
      "Timothy M Chan": {
        "avg_gpa": 3.64,
        "n": 27
      },
      "Han Zhao": {
        "avg_gpa": 3.87,
        "n": 132
      },
      "Allen H Renear": {
        "avg_gpa": 3.94,
        "n": 1313
      },
      "Yuxiong Wang": {
        "avg_gpa": 3.91,
        "n": 87
      },
      "Carl Gunter": {
        "avg_gpa": 3.88,
        "n": 22
      },
      "Dakshita Khurana": {
        "avg_gpa": 3.73,
        "n": 25
      },
      "Elahe Soltanaghai": {
        "avg_gpa": 3.91,
        "n": 25
      },
      "Ling Ren": {
        "avg_gpa": 3.58,
        "n": 65
      },
      "Ranjitha Kumar": {
        "avg_gpa": 3.84,
        "n": 155
      },
      "Eshwar Chandrasekharan": {
        "avg_gpa": 3.98,
        "n": 32
      },
      "Talia L Ringer": {
        "avg_gpa": 3.91,
        "n": 22
      },
      "Tianyin Xu": {
        "avg_gpa": 3.77,
        "n": 64
      },
      "Oluwasanmi O Koyejo": {
        "avg_gpa": 3.71,
        "n": 87
      },
      "Lui R Sha": {
        "avg_gpa": 3.82,
        "n": 49
      },
      "Nan Jiang": {
        "avg_gpa": 3.8,
        "n": 78
      },
      "Paris Smaragdis": {
        "avg_gpa": 3.81,
        "n": 457
      },
      "Hanghang Tong": {
        "avg_gpa": 3.68,
        "n": 31
      },
      "Bo Li": {
        "avg_gpa": 3.9,
        "n": 54
      },
      "Matus J Telgarsky": {
        "avg_gpa": 3.8,
        "n": 49
      },
      "Ruoqing Zhu": {
        "avg_gpa": 3.77,
        "n": 176
      },
      "Andreas P Kloeckner": {
        "avg_gpa": 3.95,
        "n": 21
      },
      "Justin A Sirignano": {
        "avg_gpa": 3.87,
        "n": 39
      },
      "Jian Peng": {
        "avg_gpa": 3.86,
        "n": 46
      },
      "Kyratso G Karahalios": {
        "avg_gpa": 3.93,
        "n": 28
      },
      "Christopher W Fletcher": {
        "avg_gpa": 3.95,
        "n": 25
      },
      "Hari Sundaram": {
        "avg_gpa": 3.89,
        "n": 24
      },
      "David A Forsyth": {
        "avg_gpa": 3.93,
        "n": 27
      },
      "Svetlana Lazebnik": {
        "avg_gpa": 3.82,
        "n": 59
      },
      "Tarek Abdelzaher": {
        "avg_gpa": 3.89,
        "n": 24
      },
      "Bertram Ludaescher": {
        "avg_gpa": 3.96,
        "n": 61
      },
      "Chengxiang Zhai": {
        "avg_gpa": 3.88,
        "n": 163
      },
      "Jeff G Erickson": {
        "avg_gpa": 3.76,
        "n": 29
      },
      "Avrim L Blum": {
        "avg_gpa": 3.67,
        "n": 24
      },
      "Laxmikant V Kale": {
        "avg_gpa": 3.64,
        "n": 23
      },
      "Sarita V Adve": {
        "avg_gpa": 3.83,
        "n": 21
      },
      "Robin A Rutenbar": {
        "avg_gpa": 3.46,
        "n": 29
      },
      "Ralph E Johnson": {
        "avg_gpa": 3.83,
        "n": 30
      }
    }
  },
  "CS 400": {
    "course_avg_gpa": 3.51,
    "professors": {
      "Tiffani L Williams": {
        "avg_gpa": 3.51,
        "n": 21
      }
    }
  },
  "CS 401": {
    "course_avg_gpa": 3.8,
    "professors": {
      "Yael Gertner": {
        "avg_gpa": 3.8,
        "n": 23
      }
    }
  },
  "CS 409": {
    "course_avg_gpa": 3.56,
    "professors": {
      "Ranjitha Kumar": {
        "avg_gpa": 3.56,
        "n": 656
      }
    }
  },
  "CS 418": {
    "course_avg_gpa": 3.28,
    "professors": {
      "Luther A Tychonievich": {
        "avg_gpa": 3.32,
        "n": 448
      },
      "Eric G Shaffer": {
        "avg_gpa": 3.16,
        "n": 1507
      },
      "John C Hart": {
        "avg_gpa": 3.41,
        "n": 1254
      }
    }
  },
  "CS 424": {
    "course_avg_gpa": 3.61,
    "professors": {
      "Tarek Abdelzaher": {
        "avg_gpa": 3.59,
        "n": 431
      },
      "Lui R Sha": {
        "avg_gpa": 3.79,
        "n": 50
      }
    }
  },
  "CS 426": {
    "course_avg_gpa": 3.42,
    "professors": {
      "Thirimadura C Mendis": {
        "avg_gpa": 3.56,
        "n": 35
      },
      "Sasa Misailovic": {
        "avg_gpa": 3.59,
        "n": 36
      },
      "Vikram S Adve": {
        "avg_gpa": 3.35,
        "n": 166
      }
    }
  },
  "CS 465": {
    "course_avg_gpa": 3.34,
    "professors": {
      "Brian P Bailey": {
        "avg_gpa": 3.39,
        "n": 1767
      },
      "Alex Kirlik": {
        "avg_gpa": 3.43,
        "n": 258
      },
      "Wai-Tat Fu": {
        "avg_gpa": 3.21,
        "n": 843
      }
    }
  },
  "CS 466": {
    "course_avg_gpa": 3.52,
    "professors": {
      "Mohammed El-Kebir": {
        "avg_gpa": 3.38,
        "n": 403
      },
      "Saurabh Sinha": {
        "avg_gpa": 3.36,
        "n": 319
      },
      "Jian Peng": {
        "avg_gpa": 3.84,
        "n": 349
      },
      "Tandy Warnow": {
        "avg_gpa": 3.11,
        "n": 21
      }
    }
  },
  "CS 470": {
    "course_avg_gpa": 3.94,
    "professors": {
      "Hari Sundaram": {
        "avg_gpa": 3.94,
        "n": 45
      }
    }
  },
  "CS 484": {
    "course_avg_gpa": 3.33,
    "professors": {
      "Lawrence Rauchwerger": {
        "avg_gpa": 3.44,
        "n": 385
      },
      "Laxmikant V Kale": {
        "avg_gpa": 3.24,
        "n": 292
      },
      "David A Padua": {
        "avg_gpa": 2.62,
        "n": 22
      }
    }
  },
  "CS 511": {
    "course_avg_gpa": 3.78,
    "professors": {
      "Yongjoo Park": {
        "avg_gpa": 3.85,
        "n": 233
      },
      "Daniel Kang": {
        "avg_gpa": 3.9,
        "n": 67
      },
      "Kevin C Chang": {
        "avg_gpa": 3.61,
        "n": 145
      }
    }
  },
  "CS 527": {
    "course_avg_gpa": 3.77,
    "professors": {
      "Darko Marinov": {
        "avg_gpa": 3.73,
        "n": 325
      },
      "Reyhaneh Jabbarvand Behr": {
        "avg_gpa": 3.87,
        "n": 69
      },
      "Lingming Zhang": {
        "avg_gpa": 3.83,
        "n": 28
      },
      "Tao Xie": {
        "avg_gpa": 3.8,
        "n": 94
      }
    }
  },
  "CS 537": {
    "course_avg_gpa": 3.61,
    "professors": {
      "Klara Nahrstedt": {
        "avg_gpa": 3.61,
        "n": 37
      }
    }
  },
  "CS 542": {
    "course_avg_gpa": 3.61,
    "professors": {
      "Nan Jiang": {
        "avg_gpa": 3.61,
        "n": 199
      }
    }
  },
  "CS 545": {
    "course_avg_gpa": 3.74,
    "professors": {
      "Minje Kim": {
        "avg_gpa": 3.73,
        "n": 72
      },
      "Paris Smaragdis": {
        "avg_gpa": 3.75,
        "n": 131
      }
    }
  },
  "CS 546": {
    "course_avg_gpa": 3.82,
    "professors": {
      "Heng Ji": {
        "avg_gpa": 3.81,
        "n": 432
      },
      "Julia C Hockenmaier": {
        "avg_gpa": 3.9,
        "n": 110
      },
      "Dan Roth": {
        "avg_gpa": 3.75,
        "n": 60
      }
    }
  },
  "CS 562": {
    "course_avg_gpa": 3.89,
    "professors": {
      "Gang Wang": {
        "avg_gpa": 3.89,
        "n": 92
      },
      "Varun Chandrasekaran": {
        "avg_gpa": 3.89,
        "n": 28
      },
      "Bo Li": {
        "avg_gpa": 3.9,
        "n": 21
      }
    }
  },
  "CS 567": {
    "course_avg_gpa": 3.79,
    "professors": {
      "Kyratso G Karahalios": {
        "avg_gpa": 3.79,
        "n": 107
      }
    }
  },
  "CS 199": {
    "course_avg_gpa": 3.72,
    "professors": {
      "Jule Schatz": {
        "avg_gpa": 3.89,
        "n": 37
      },
      "Joshua T Asplund": {
        "avg_gpa": 3.91,
        "n": 22
      },
      "Colleen M Lewis": {
        "avg_gpa": 3.9,
        "n": 40
      },
      "Michael Nowak": {
        "avg_gpa": 3.45,
        "n": 69
      },
      "Mariana T Silva": {
        "avg_gpa": 3.86,
        "n": 119
      },
      "Eric G Shaffer": {
        "avg_gpa": 3.61,
        "n": 95
      },
      "Neal E Davis": {
        "avg_gpa": 3.75,
        "n": 28
      },
      "Lawrence C Angrave": {
        "avg_gpa": 3.71,
        "n": 263
      },
      "Cinda Heeren": {
        "avg_gpa": 3.69,
        "n": 114
      },
      "Ganna Yershova": {
        "avg_gpa": 3.69,
        "n": 26
      },
      "Craig Zilles": {
        "avg_gpa": 3.9,
        "n": 29
      }
    }
  },
  "CS 443": {
    "course_avg_gpa": 3.19,
    "professors": {
      "Nan Jiang": {
        "avg_gpa": 3.19,
        "n": 130
      }
    }
  },
  "CS 467": {
    "course_avg_gpa": 3.74,
    "professors": {
      "Kyratso G Karahalios": {
        "avg_gpa": 3.74,
        "n": 494
      }
    }
  },
  "CS 512": {
    "course_avg_gpa": 3.61,
    "professors": {
      "Hanghang Tong": {
        "avg_gpa": 3.38,
        "n": 197
      },
      "Jiawei Han": {
        "avg_gpa": 3.68,
        "n": 630
      }
    }
  },
  "CS 565": {
    "course_avg_gpa": 3.72,
    "professors": {
      "Sharifa Sultana": {
        "avg_gpa": 3.68,
        "n": 33
      },
      "Brian P Bailey": {
        "avg_gpa": 3.72,
        "n": 265
      }
    }
  },
  "CS 574": {
    "course_avg_gpa": 3.62,
    "professors": {
      "Sariel Har-Peled": {
        "avg_gpa": 3.61,
        "n": 44
      },
      "Timothy M Chan": {
        "avg_gpa": 3.63,
        "n": 30
      }
    }
  },
  "CS 416": {
    "course_avg_gpa": 3.84,
    "professors": {
      "John C Hart": {
        "avg_gpa": 3.84,
        "n": 1451
      }
    }
  },
  "CS 519": {
    "course_avg_gpa": 3.74,
    "professors": {
      "Eric G Shaffer": {
        "avg_gpa": 3.74,
        "n": 951
      }
    }
  },
  "CS 100": {
    "course_avg_gpa": 3.76,
    "professors": {
      "Margaret M Fleck": {
        "avg_gpa": 3.9,
        "n": 740
      },
      "Elsa Gunter": {
        "avg_gpa": 3.8,
        "n": 1464
      },
      "Leonard B Pitt": {
        "avg_gpa": 3.69,
        "n": 2102
      }
    }
  },
  "CS 460": {
    "course_avg_gpa": 3.67,
    "professors": {
      "Charles W O'Brien": {
        "avg_gpa": 3.95,
        "n": 21
      },
      "John C Bambenek": {
        "avg_gpa": 3.67,
        "n": 557
      },
      "Susan Hinrichs": {
        "avg_gpa": 3.57,
        "n": 74
      }
    }
  },
  "CS 580": {
    "course_avg_gpa": 3.52,
    "professors": {
      "Ruta Mehta": {
        "avg_gpa": 3.52,
        "n": 53
      }
    }
  },
  "CS 402": {
    "course_avg_gpa": 3.71,
    "professors": {
      "Tiffani L Williams": {
        "avg_gpa": 3.71,
        "n": 25
      }
    }
  },
  "CS 403": {
    "course_avg_gpa": 3.53,
    "professors": {
      "Yael Gertner": {
        "avg_gpa": 3.53,
        "n": 27
      }
    }
  },
  "CS 420": {
    "course_avg_gpa": 3.37,
    "professors": {
      "Raghavendra Kanakagiri": {
        "avg_gpa": 3.61,
        "n": 117
      },
      "David A Padua": {
        "avg_gpa": 3.37,
        "n": 127
      },
      "Marc Snir": {
        "avg_gpa": 2.95,
        "n": 81
      },
      "Laxmikant V Kale": {
        "avg_gpa": 3.39,
        "n": 172
      }
    }
  },
  "CS 469": {
    "course_avg_gpa": 3.91,
    "professors": {
      "Hari Sundaram": {
        "avg_gpa": 3.91,
        "n": 75
      }
    }
  },
  "CS 525": {
    "course_avg_gpa": 3.69,
    "professors": {
      "Indranil Gupta": {
        "avg_gpa": 3.69,
        "n": 463
      }
    }
  },
  "CS 476": {
    "course_avg_gpa": 3.57,
    "professors": {
      "Jose Meseguer": {
        "avg_gpa": 3.57,
        "n": 24
      }
    }
  },
  "CS 540": {
    "course_avg_gpa": 3.82,
    "professors": {
      "Matus J Telgarsky": {
        "avg_gpa": 3.82,
        "n": 56
      }
    }
  },
  "CS 126": {
    "course_avg_gpa": 3.51,
    "professors": {
      "Michael J Woodley": {
        "avg_gpa": 3.58,
        "n": 1167
      },
      "Graham C Evans": {
        "avg_gpa": 3.49,
        "n": 685
      },
      "Craig Zilles": {
        "avg_gpa": 3.43,
        "n": 145
      },
      "Lawrence C Angrave": {
        "avg_gpa": 3.31,
        "n": 261
      }
    }
  },
  "CS 240": {
    "course_avg_gpa": 3.32,
    "professors": {
      "Wade A Fagen-Ulmschnei": {
        "avg_gpa": 3.32,
        "n": 182
      }
    }
  },
  "CS 241": {
    "course_avg_gpa": 2.85,
    "professors": {
      "Lawrence Angrave": {
        "avg_gpa": 3.43,
        "n": 1203
      },
      "Lawrence C Angrave": {
        "avg_gpa": 2.79,
        "n": 2325
      },
      "Graham C Evans": {
        "avg_gpa": 2.61,
        "n": 489
      },
      "Marco Caccamo": {
        "avg_gpa": 2.55,
        "n": 463
      },
      "Wade A Fagen": {
        "avg_gpa": 2.55,
        "n": 224
      },
      "Robin H Kravets": {
        "avg_gpa": 2.4,
        "n": 542
      }
    }
  },
  "CS 475": {
    "course_avg_gpa": 3.49,
    "professors": {
      "Benjamin L Cosman": {
        "avg_gpa": 3.49,
        "n": 24
      }
    }
  },
  "CS 196": {
    "course_avg_gpa": 3.79,
    "professors": {
      "Geoffrey W Challen": {
        "avg_gpa": 3.85,
        "n": 986
      },
      "Margaret M Fleck": {
        "avg_gpa": 3.64,
        "n": 314
      },
      "William L Chapman": {
        "avg_gpa": 3.82,
        "n": 697
      },
      "Lawrence C Angrave": {
        "avg_gpa": 3.77,
        "n": 332
      },
      "Viraj Kumar": {
        "avg_gpa": 2.75,
        "n": 27
      },
      "Thomas N Gambill": {
        "avg_gpa": 3.92,
        "n": 48
      }
    }
  },
  "CS 242": {
    "course_avg_gpa": 3.43,
    "professors": {
      "Michael J Woodley": {
        "avg_gpa": 3.43,
        "n": 3350
      }
    }
  },
  "CS 554": {
    "course_avg_gpa": 3.69,
    "professors": {
      "Edgar V Solomonik": {
        "avg_gpa": 3.83,
        "n": 67
      },
      "Michael T Heath": {
        "avg_gpa": 3.6,
        "n": 100
      }
    }
  },
  "CS 579": {
    "course_avg_gpa": 3.63,
    "professors": {
      "Michael A Forbes": {
        "avg_gpa": 3.63,
        "n": 71
      }
    }
  },
  "CS 583": {
    "course_avg_gpa": 3.75,
    "professors": {
      "Chandra S Chekuri": {
        "avg_gpa": 3.75,
        "n": 61
      }
    }
  },
  "CS 125": {
    "course_avg_gpa": 3.39,
    "professors": {
      "Geoffrey W Challen": {
        "avg_gpa": 3.54,
        "n": 4125
      },
      "Lawrence C Angrave": {
        "avg_gpa": 3.19,
        "n": 2610
      },
      "William L Chapman": {
        "avg_gpa": 3.4,
        "n": 3215
      },
      "Craig Zilles": {
        "avg_gpa": 3.11,
        "n": 406
      },
      "Navin Fogla": {
        "avg_gpa": 2.68,
        "n": 24
      },
      "Sharat Nagaraja": {
        "avg_gpa": 3.24,
        "n": 66
      },
      "Nisha Somnath": {
        "avg_gpa": 2.93,
        "n": 28
      }
    }
  },
  "CS 296": {
    "course_avg_gpa": 3.69,
    "professors": {
      "Brad R Solomon": {
        "avg_gpa": 3.82,
        "n": 155
      },
      "Graham C Evans": {
        "avg_gpa": 3.64,
        "n": 70
      },
      "Wade A Fagen-Ulmschnei": {
        "avg_gpa": 3.79,
        "n": 323
      },
      "Craig Zilles": {
        "avg_gpa": 3.34,
        "n": 182
      },
      "Cinda Heeren": {
        "avg_gpa": 3.71,
        "n": 487
      },
      "Lawrence C Angrave": {
        "avg_gpa": 3.78,
        "n": 123
      }
    }
  },
  "CS 419": {
    "course_avg_gpa": 3.44,
    "professors": {
      "Eric G Shaffer": {
        "avg_gpa": 3.48,
        "n": 125
      },
      "David A Forsyth": {
        "avg_gpa": 3.23,
        "n": 25
      }
    }
  },
  "CS 513": {
    "course_avg_gpa": 3.96,
    "professors": {
      "Bertram Ludaescher": {
        "avg_gpa": 3.96,
        "n": 780
      }
    }
  },
  "CS 398": {
    "course_avg_gpa": 2.93,
    "professors": {
      "Justin A Sirignano": {
        "avg_gpa": 3.92,
        "n": 42
      },
      "Victoria Stodden": {
        "avg_gpa": 3.55,
        "n": 29
      },
      "Robert J Brunner": {
        "avg_gpa": 3.41,
        "n": 60
      },
      "Craig Zilles": {
        "avg_gpa": 2.85,
        "n": 748
      },
      "Maria J Garzaran": {
        "avg_gpa": 2.81,
        "n": 193
      }
    }
  },
  "CS 429": {
    "course_avg_gpa": 3.42,
    "professors": {
      "Darko Marinov": {
        "avg_gpa": 3.46,
        "n": 255
      },
      "Tao Xie": {
        "avg_gpa": 3.43,
        "n": 210
      },
      "Daniel Dig": {
        "avg_gpa": 3.26,
        "n": 108
      },
      "Ralph E Johnson": {
        "avg_gpa": 3.51,
        "n": 72
      }
    }
  },
  "CS 548": {
    "course_avg_gpa": 3.39,
    "professors": {
      "Wai-Tat Fu": {
        "avg_gpa": 3.39,
        "n": 96
      }
    }
  },
  "CS 492": {
    "course_avg_gpa": 3.52,
    "professors": {
      "Michael J Woodley": {
        "avg_gpa": 3.52,
        "n": 527
      }
    }
  },
  "CS 493": {
    "course_avg_gpa": 3.63,
    "professors": {
      "Michael J Woodley": {
        "avg_gpa": 3.63,
        "n": 373
      }
    }
  },
  "CS 428": {
    "course_avg_gpa": 3.51,
    "professors": {
      "Tao Xie": {
        "avg_gpa": 3.67,
        "n": 69
      },
      "Darko Marinov": {
        "avg_gpa": 3.38,
        "n": 78
      },
      "Daniel Dig": {
        "avg_gpa": 3.32,
        "n": 28
      },
      "Ralph E Johnson": {
        "avg_gpa": 3.67,
        "n": 24
      }
    }
  },
  "CS 494": {
    "course_avg_gpa": 3.61,
    "professors": {
      "Michael J Woodley": {
        "avg_gpa": 3.61,
        "n": 50
      }
    }
  },
  "CS 528": {
    "course_avg_gpa": 3.6,
    "professors": {
      "Craig Zilles": {
        "avg_gpa": 3.51,
        "n": 46
      },
      "Ralph E Johnson": {
        "avg_gpa": 3.71,
        "n": 41
      }
    }
  },
  "CS 556": {
    "course_avg_gpa": 3.56,
    "professors": {
      "Luke Olson": {
        "avg_gpa": 3.56,
        "n": 27
      }
    }
  },
  "CS 373": {
    "course_avg_gpa": 3.01,
    "professors": {
      "Jose Meseguer": {
        "avg_gpa": 2.84,
        "n": 143
      },
      "Mahesh Viswanathan": {
        "avg_gpa": 3.18,
        "n": 698
      },
      "Joseph Di Febo": {
        "avg_gpa": 3.32,
        "n": 42
      },
      "Ryan M Cunningham": {
        "avg_gpa": 3.21,
        "n": 78
      },
      "Madhusudan Parthasarathy": {
        "avg_gpa": 2.61,
        "n": 268
      },
      "Steven M Lavalle": {
        "avg_gpa": 2.87,
        "n": 105
      },
      "Viraj Kumar": {
        "avg_gpa": 2.92,
        "n": 26
      }
    }
  },
  "CS 414": {
    "course_avg_gpa": 3.21,
    "professors": {
      "Klara Nahrstedt": {
        "avg_gpa": 3.21,
        "n": 105
      }
    }
  },
  "CS 544": {
    "course_avg_gpa": 3.96,
    "professors": {
      "David A Forsyth": {
        "avg_gpa": 3.96,
        "n": 31
      }
    }
  },
  "CS 422": {
    "course_avg_gpa": 3.79,
    "professors": {
      "Grigore Rosu": {
        "avg_gpa": 3.79,
        "n": 22
      }
    }
  },
  "CS 573": {
    "course_avg_gpa": 3.51,
    "professors": {
      "Sariel Har-Peled": {
        "avg_gpa": 3.47,
        "n": 59
      },
      "Chandra S Chekuri": {
        "avg_gpa": 3.55,
        "n": 37
      },
      "Jeff G Erickson": {
        "avg_gpa": 3.51,
        "n": 53
      }
    }
  },
  "CS 231": {
    "course_avg_gpa": 2.73,
    "professors": {
      "Maria J Garzaran": {
        "avg_gpa": 2.74,
        "n": 324
      },
      "Laxmikant V Kale": {
        "avg_gpa": 2.71,
        "n": 313
      }
    }
  },
  "CS 232": {
    "course_avg_gpa": 3.21,
    "professors": {
      "Craig Zilles": {
        "avg_gpa": 2.91,
        "n": 132
      },
      "Viraj Kumar": {
        "avg_gpa": 3.31,
        "n": 281
      },
      "Ryan M Cunningham": {
        "avg_gpa": 3.35,
        "n": 39
      },
      "Abner Guzman Rivera": {
        "avg_gpa": 3.12,
        "n": 40
      },
      "Arushi Aggarwal": {
        "avg_gpa": 3.54,
        "n": 28
      },
      "Pritam P Sukumar": {
        "avg_gpa": 3.26,
        "n": 39
      }
    }
  },
  "CS 457": {
    "course_avg_gpa": 2.63,
    "professors": {
      "William D Gropp": {
        "avg_gpa": 2.63,
        "n": 24
      }
    }
  }
}